ckitoolz/__init__.pxd
ckitoolz/__init__.py
ckitoolz/__version__.py
ckitoolz/_signatures.py
ckitoolz/_version.py
ckitoolz/compatibility.py
ckitoolz/cpython.pxd
ckitoolz/dicttoolz.cpython-37m-darwin.so
ckitoolz/dicttoolz.pxd
ckitoolz/dicttoolz.pyx
ckitoolz/functoolz.cpython-37m-darwin.so
ckitoolz/functoolz.pxd
ckitoolz/functoolz.pyx
ckitoolz/itertoolz.cpython-37m-darwin.so
ckitoolz/itertoolz.pxd
ckitoolz/itertoolz.pyx
ckitoolz/recipes.cpython-37m-darwin.so
ckitoolz/recipes.pxd
ckitoolz/recipes.pyx
ckitoolz/utils.cpython-37m-darwin.so
ckitoolz/utils.pxd
ckitoolz/utils.pyx
ckitoolz/curried/__init__.py
ckitoolz/curried/exceptions.py
ckitoolz/curried/operator.py
ckitoolz/tests/dev_skip_test.py
ckitoolz/tests/test_compatibility.py
ckitoolz/tests/test_curried.py
ckitoolz/tests/test_curried_toolzlike.py
ckitoolz/tests/test_dev_skip_test.py
ckitoolz/tests/test_dicttoolz.py
ckitoolz/tests/test_docstrings.py
ckitoolz/tests/test_doctests.py
ckitoolz/tests/test_embedded_sigs.py
ckitoolz/tests/test_functoolz.py
ckitoolz/tests/test_inspect_args.py
ckitoolz/tests/test_itertoolz.py
ckitoolz/tests/test_none_safe.py
ckitoolz/tests/test_recipes.py
ckitoolz/tests/test_serialization.py
ckitoolz/tests/test_signatures.py
ckitoolz/tests/test_tlz.py
ckitoolz/tests/test_utils.py
ckitoolz-0.1.1.dist-info/AUTHORS.md
ckitoolz-0.1.1.dist-info/LICENSE.txt
ckitoolz-0.1.1.dist-info/METADATA
ckitoolz-0.1.1.dist-info/WHEEL
ckitoolz-0.1.1.dist-info/top_level.txt
ckitoolz-0.1.1.dist-info/RECORD
