Metadata-Version: 2.1
Name: ckitoolz
Version: 0.1.1
Summary: Cython implementation of Kitoolz: High performance functional utilities
Home-page: https://github.com/szj2ys/ckitoolz.git
Author: https://raw.github.com/pytoolz/cytoolz/master/AUTHORS.md
Author-email: erik.n.welch@gmail.com
Maintainer: Erik Welch
Maintainer-email: erik.n.welch@gmail.com
License: BSD
Keywords: functional utility itertools functools iterator generator curry memoize lazy streaming bigdata cython toolz ckitoolz
Platform: UNKNOWN
Classifier: Development Status :: 5 - Production/Stable
Classifier: Intended Audience :: Developers
Classifier: Intended Audience :: Education
Classifier: Intended Audience :: Science/Research
Classifier: License :: OSI Approved :: BSD License
Classifier: Operating System :: OS Independent
Classifier: Programming Language :: Cython
Classifier: Programming Language :: Python
Classifier: Programming Language :: Python :: 3
Classifier: Programming Language :: Python :: 3.5
Classifier: Programming Language :: Python :: 3.6
Classifier: Programming Language :: Python :: 3.7
Classifier: Programming Language :: Python :: 3.8
Classifier: Topic :: Scientific/Engineering
Classifier: Topic :: Scientific/Engineering :: Information Analysis
Classifier: Topic :: Software Development
Classifier: Topic :: Software Development :: Libraries
Classifier: Topic :: Software Development :: Libraries :: Python Modules
Classifier: Topic :: Utilities
Requires-Python: >=3.5
Requires-Dist: kitoolz (>=0.1.2)
Provides-Extra: cython
Requires-Dist: cython ; extra == 'cython'
